pyvenvwrapper/__init__.py
pyvenvwrapper/install.py
pyvenvwrapper/pyvenvwrapper
pyvenvwrapper/pyvenvwrapper_settings
pyvenvwrapper-1.0.0.dist-info/DESCRIPTION.rst
pyvenvwrapper-1.0.0.dist-info/METADATA
pyvenvwrapper-1.0.0.dist-info/RECORD
pyvenvwrapper-1.0.0.dist-info/WHEEL
pyvenvwrapper-1.0.0.dist-info/entry_points.txt
pyvenvwrapper-1.0.0.dist-info/metadata.json
pyvenvwrapper-1.0.0.dist-info/top_level.txt
